LICENSE
README.md
setup.py
damilu_baseline/BIDFC_tool.py
damilu_baseline/__init__.py
damilu_baseline/byol_tool.py
damilu_baseline/general_tool.py
damilu_baseline/moco_tool.py
damilu_baseline/simclr_tool.py
damilu_baseline/simsiam_tool.py
damilu_baseline/swav_tool.py
damilu_baseline.egg-info/PKG-INFO
damilu_baseline.egg-info/SOURCES.txt
damilu_baseline.egg-info/dependency_links.txt
damilu_baseline.egg-info/top_level.txt